sparkly/__init__.py
sparkly/catalog.py
sparkly/exceptions.py
sparkly/functions.py
sparkly/instant_testing.py
sparkly/reader.py
sparkly/session.py
sparkly/testing.py
sparkly/utils.py
sparkly/writer.py
sparkly-2.4.1.data/scripts/sparkly-testing
sparkly-2.4.1.dist-info/DESCRIPTION.rst
sparkly-2.4.1.dist-info/METADATA
sparkly-2.4.1.dist-info/RECORD
sparkly-2.4.1.dist-info/WHEEL
sparkly-2.4.1.dist-info/metadata.json
sparkly-2.4.1.dist-info/top_level.txt
