Metadata-Version: 2.0
Name: sparkly
Version: 2.4.1
Summary: Helpers & syntax sugar for PySpark.
Home-page: https://github.com/Tubular/sparkly
Author: Tubular Engineering
Author-email: dev@tubularlabs.com
License: Apache License 2.0
Keywords: sparkly spark pyspark
Platform: UNKNOWN
Classifier: Development Status :: 3 - Alpha
Classifier: Intended Audience :: Developers
Classifier: Topic :: Software Development :: Build Tools
Classifier: License :: OSI Approved :: Apache Software License
Classifier: Programming Language :: Python :: 2
Classifier: Programming Language :: Python :: 2.7
Classifier: Programming Language :: Python :: 3
Classifier: Programming Language :: Python :: 3.5
Provides-Extra: kafka
Provides-Extra: test
Provides-Extra: redis
Requires-Dist: pylru (==1.0.9)
Requires-Dist: six (==1.10.0)
Provides-Extra: kafka
Requires-Dist: kafka-python (<1.3,>=1.2.2); extra == 'kafka'
Provides-Extra: redis
Requires-Dist: redis (>=2.10,<3); extra == 'redis'
Requires-Dist: ujson (<2,>=1.33); extra == 'redis'
Provides-Extra: test
Requires-Dist: PyMySQL (<0.8,>=0.7); extra == 'test'
Requires-Dist: cassandra-driver (<3.8,>=3.7); extra == 'test'
Requires-Dist: kafka-python (<1.3,>=1.2.2); extra == 'test'
Requires-Dist: redis (>=2.10,<3); extra == 'test'
Requires-Dist: ujson (<2,>=1.33); extra == 'test'
